{
    "id": "5ced4b05a2a05a0001aca816",
    "rbd": 1966,
    "nombre": "ESCUELA BASICA CATALUNYA",
    "dependencia": "PUBLICO",
    "telefono": "2730820",
    "mail": "CATALUNYA@CMVA.CL",
    "url": "WWW.ESCUELACATALUNYA.CL",
    "habilitadoPostular": true,
    "habilitadoVitrina": true,
    "nivelMinimo": "Pre-Kinder",
    "nivelMaximo": "8\u00ba B\u00e1sico",
    "director": {
        "nombre": "ANDR\u00c9S EDUARDO BRIGNARDELLO VALDIVIA"
    },
    "etiquetas": [
        "PIE",
        "SEP",
        "GRATUITO"
    ],
    "informacionInstitucional": {
        "resumenProyecto": "",
        "documentoProyecto": "ProyectoEducativo1966.pdf",
        "documentoReglamento": "ReglamentodeConvivencia1966.pdf",
        "internado": false,
        "integracion": true,
        "subvencionPreferencial": true,
        "peib": false,
        "politicaUniforme": "Uniforme regular",
        "orientacionReligiosa": "Laica",
        "alumnosMatriculados": 281,
        "promedioAlumnosPorCurso": 28,
        "cantidadDocentes": 33,
        "regimen": "Mixto"
    },
    "sedes": [
        {
            "codigoSede": 1,
            "direccion": {
                "codigoRegion": 5,
                "codigoComuna": 5804,
                "region": "De Valpara\u00edso",
                "comuna": "Villa Alemana",
                "calle": "BAQUEDANO 618 PE\u00d1ABLANCA 618",
                "coordenadas": {
                    "type": "Point",
                    "coordinates": [
                        -71.35595,
                        -33.04208
                    ]
                }
            },
            "niveles": [
                {
                    "codigoCurso": 401000000131,
                    "glosaGrupoEnsenanza": "Educaci\u00f3n Parvularia",
                    "glosaEnsenanza": "Educaci\u00f3n Parvularia",
                    "glosaNivel": "1er nivel de Transici\u00f3n (Pre-kinder)",
                    "etiquetaNivel": "PREKINDER",
                    "sexo": "MIXTO",
                    "glosaJornada": "MA\u00d1ANA",
                    "glosaEspecialidad": null,
                    "glosaGrupoPago": "PARVULARIA",
                    "codigoEnsenanza": 10,
                    "codigoNivel": 4,
                    "codigoJornada": 1,
                    "codigoSexo": 3,
                    "codigoEspecialidad": 0,
                    "unicoComuna": false,
                    "proporcionExcelenciaTransicion": null,
                    "proporcionExcelenciaRegimen": null,
                    "proporcionEspecializacionTemprana": null,
                    "copago": {
                        "numeroCuotas": 0,
                        "valorCuota": 0
                    },
                    "cuposTotales": 10,
                    "numeroVacantesRangoInferior": 10,
                    "numeroVacantesRangoSuperior": 10,
                    "porcentajeCambioInferior": 0.0,
                    "procentajeCambioSuperior": 0.0,
                    "cantidadRepitentesAnioActual": 0,
                    "cantidadRepitentesNivelAnterior": 0,
                    "cantidadPreInscritosAnioSiguiente": 0,
                    "cambiosInferior": 0,
                    "cambiosSuperior": 0,
                    "cantidadPreVacantesInferior": 10,
                    "cantidadPreVacantesSuperior": 10,
                    "rango": 0,
                    "numeroPostulantesAnioAnterior": 20,
                    "numeroMovimientoListaEsperaAnoAnterior": 0
                },
                {
                    "codigoCurso": 501000000131,
                    "glosaGrupoEnsenanza": "Educaci\u00f3n Parvularia",
                    "glosaEnsenanza": "Educaci\u00f3n Parvularia",
                    "glosaNivel": "2\u00b0 nivel de Transici\u00f3n (Kinder)",
                    "etiquetaNivel": "KINDER",
                    "sexo": "MIXTO",
                    "glosaJornada": "MA\u00d1ANA",
                    "glosaEspecialidad": null,
                    "glosaGrupoPago": "PARVULARIA",
                    "codigoEnsenanza": 10,
                    "codigoNivel": 5,
                    "codigoJornada": 1,
                    "codigoSexo": 3,
                    "codigoEspecialidad": 0,
                    "unicoComuna": false,
                    "proporcionExcelenciaTransicion": null,
                    "proporcionExcelenciaRegimen": null,
                    "proporcionEspecializacionTemprana": null,
                    "copago": {
                        "numeroCuotas": 0,
                        "valorCuota": 0
                    },
                    "cuposTotales": 20,
                    "numeroVacantesRangoInferior": 10,
                    "numeroVacantesRangoSuperior": 13,
                    "porcentajeCambioInferior": 0.1018518518,
                    "procentajeCambioSuperior": 0.20119047610000002,
                    "cantidadRepitentesAnioActual": 0,
                    "cantidadRepitentesNivelAnterior": 0,
                    "cantidadPreInscritosAnioSiguiente": 10,
                    "cambiosInferior": 1,
                    "cambiosSuperior": 2,
                    "cantidadPreVacantesInferior": 10,
                    "cantidadPreVacantesSuperior": 13,
                    "rango": 1,
                    "numeroPostulantesAnioAnterior": 9,
                    "numeroMovimientoListaEsperaAnoAnterior": 0
                },
                {
                    "codigoCurso": 111000000131,
                    "glosaGrupoEnsenanza": "Educaci\u00f3n B\u00e1sica",
                    "glosaEnsenanza": "Ense\u00f1anza B\u00e1sica",
                    "glosaNivel": "1\u00b0 b\u00e1sico",
                    "etiquetaNivel": "1BASICO",
                    "sexo": "MIXTO",
                    "glosaJornada": "MA\u00d1ANA",
                    "glosaEspecialidad": null,
                    "glosaGrupoPago": "BASICA",
                    "codigoEnsenanza": 110,
                    "codigoNivel": 1,
                    "codigoJornada": 1,
                    "codigoSexo": 3,
                    "codigoEspecialidad": 0,
                    "unicoComuna": false,
                    "proporcionExcelenciaTransicion": null,
                    "proporcionExcelenciaRegimen": null,
                    "proporcionEspecializacionTemprana": null,
                    "copago": {
                        "numeroCuotas": 0,
                        "valorCuota": 0
                    },
                    "cuposTotales": 38,
                    "numeroVacantesRangoInferior": 25,
                    "numeroVacantesRangoSuperior": 28,
                    "porcentajeCambioInferior": 0.14743589740000002,
                    "procentajeCambioSuperior": 0.2547123015,
                    "cantidadRepitentesAnioActual": 0,
                    "cantidadRepitentesNivelAnterior": 0,
                    "cantidadPreInscritosAnioSiguiente": 16,
                    "cambiosInferior": 2,
                    "cambiosSuperior": 4,
                    "cantidadPreVacantesInferior": 24,
                    "cantidadPreVacantesSuperior": 27,
                    "rango": 2,
                    "numeroPostulantesAnioAnterior": 22,
                    "numeroMovimientoListaEsperaAnoAnterior": 0
                },
                {
                    "codigoCurso": 211000000131,
                    "glosaGrupoEnsenanza": "Educaci\u00f3n B\u00e1sica",
                    "glosaEnsenanza": "Ense\u00f1anza B\u00e1sica",
                    "glosaNivel": "2\u00b0 b\u00e1sico",
                    "etiquetaNivel": "2BASICO",
                    "sexo": "MIXTO",
                    "glosaJornada": "MA\u00d1ANA",
                    "glosaEspecialidad": null,
                    "glosaGrupoPago": "BASICA",
                    "codigoEnsenanza": 110,
                    "codigoNivel": 2,
                    "codigoJornada": 1,
                    "codigoSexo": 3,
                    "codigoEspecialidad": 0,
                    "unicoComuna": false,
                    "proporcionExcelenciaTransicion": null,
                    "proporcionExcelenciaRegimen": null,
                    "proporcionEspecializacionTemprana": null,
                    "copago": {
                        "numeroCuotas": 0,
                        "valorCuota": 0
                    },
                    "cuposTotales": 38,
                    "numeroVacantesRangoInferior": 10,
                    "numeroVacantesRangoSuperior": 13,
                    "porcentajeCambioInferior": 0.1273707918,
                    "procentajeCambioSuperior": 0.22381864620000003,
                    "cantidadRepitentesAnioActual": 0,
                    "cantidadRepitentesNivelAnterior": 0,
                    "cantidadPreInscritosAnioSiguiente": 30,
                    "cambiosInferior": 4,
                    "cambiosSuperior": 7,
                    "cantidadPreVacantesInferior": 12,
                    "cantidadPreVacantesSuperior": 15,
                    "rango": 3,
                    "numeroPostulantesAnioAnterior": null,
                    "numeroMovimientoListaEsperaAnoAnterior": null
                },
                {
                    "codigoCurso": 311000000133,
                    "glosaGrupoEnsenanza": "Educaci\u00f3n B\u00e1sica",
                    "glosaEnsenanza": "Ense\u00f1anza B\u00e1sica",
                    "glosaNivel": "3\u00b0 b\u00e1sico",
                    "etiquetaNivel": "3BASICO",
                    "sexo": "MIXTO",
                    "glosaJornada": "COMPLETA",
                    "glosaEspecialidad": null,
                    "glosaGrupoPago": "BASICA",
                    "codigoEnsenanza": 110,
                    "codigoNivel": 3,
                    "codigoJornada": 3,
                    "codigoSexo": 3,
                    "codigoEspecialidad": 0,
                    "unicoComuna": false,
                    "proporcionExcelenciaTransicion": null,
                    "proporcionExcelenciaRegimen": null,
                    "proporcionEspecializacionTemprana": null,
                    "copago": {
                        "numeroCuotas": 0,
                        "valorCuota": 0
                    },
                    "cuposTotales": 38,
                    "numeroVacantesRangoInferior": 10,
                    "numeroVacantesRangoSuperior": 13,
                    "porcentajeCambioInferior": 0.0952886247,
                    "procentajeCambioSuperior": 0.1647368421,
                    "cantidadRepitentesAnioActual": 0,
                    "cantidadRepitentesNivelAnterior": 0,
                    "cantidadPreInscritosAnioSiguiente": 31,
                    "cambiosInferior": 3,
                    "cambiosSuperior": 5,
                    "cantidadPreVacantesInferior": 10,
                    "cantidadPreVacantesSuperior": 13,
                    "rango": 2,
                    "numeroPostulantesAnioAnterior": 4,
                    "numeroMovimientoListaEsperaAnoAnterior": 0
                },
                {
                    "codigoCurso": 411000000133,
                    "glosaGrupoEnsenanza": "Educaci\u00f3n B\u00e1sica",
                    "glosaEnsenanza": "Ense\u00f1anza B\u00e1sica",
                    "glosaNivel": "4\u00b0 b\u00e1sico",
                    "etiquetaNivel": "4BASICO",
                    "sexo": "MIXTO",
                    "glosaJornada": "COMPLETA",
                    "glosaEspecialidad": null,
                    "glosaGrupoPago": "BASICA",
                    "codigoEnsenanza": 110,
                    "codigoNivel": 4,
                    "codigoJornada": 3,
                    "codigoSexo": 3,
                    "codigoEspecialidad": 0,
                    "unicoComuna": false,
                    "proporcionExcelenciaTransicion": null,
                    "proporcionExcelenciaRegimen": null,
                    "proporcionEspecializacionTemprana": null,
                    "copago": {
                        "numeroCuotas": 0,
                        "valorCuota": 0
                    },
                    "cuposTotales": 38,
                    "numeroVacantesRangoInferior": 15,
                    "numeroVacantesRangoSuperior": 18,
                    "porcentajeCambioInferior": 0.1258547008,
                    "procentajeCambioSuperior": 0.1832983193,
                    "cantidadRepitentesAnioActual": 0,
                    "cantidadRepitentesNivelAnterior": 0,
                    "cantidadPreInscritosAnioSiguiente": 24,
                    "cambiosInferior": 3,
                    "cambiosSuperior": 4,
                    "cantidadPreVacantesInferior": 16,
                    "cantidadPreVacantesSuperior": 19,
                    "rango": 1,
                    "numeroPostulantesAnioAnterior": 3,
                    "numeroMovimientoListaEsperaAnoAnterior": 0
                },
                {
                    "codigoCurso": 511000000133,
                    "glosaGrupoEnsenanza": "Educaci\u00f3n B\u00e1sica",
                    "glosaEnsenanza": "Ense\u00f1anza B\u00e1sica",
                    "glosaNivel": "5\u00b0 b\u00e1sico",
                    "etiquetaNivel": "5BASICO",
                    "sexo": "MIXTO",
                    "glosaJornada": "COMPLETA",
                    "glosaEspecialidad": null,
                    "glosaGrupoPago": "BASICA",
                    "codigoEnsenanza": 110,
                    "codigoNivel": 5,
                    "codigoJornada": 3,
                    "codigoSexo": 3,
                    "codigoEspecialidad": 0,
                    "unicoComuna": false,
                    "proporcionExcelenciaTransicion": null,
                    "proporcionExcelenciaRegimen": null,
                    "proporcionEspecializacionTemprana": null,
                    "copago": {
                        "numeroCuotas": 0,
                        "valorCuota": 0
                    },
                    "cuposTotales": 38,
                    "numeroVacantesRangoInferior": 10,
                    "numeroVacantesRangoSuperior": 15,
                    "porcentajeCambioInferior": 0.06006006,
                    "procentajeCambioSuperior": 0.235042735,
                    "cantidadRepitentesAnioActual": 0,
                    "cantidadRepitentesNivelAnterior": 0,
                    "cantidadPreInscritosAnioSiguiente": 30,
                    "cambiosInferior": 2,
                    "cambiosSuperior": 7,
                    "cantidadPreVacantesInferior": 10,
                    "cantidadPreVacantesSuperior": 15,
                    "rango": 5,
                    "numeroPostulantesAnioAnterior": 2,
                    "numeroMovimientoListaEsperaAnoAnterior": 0
                },
                {
                    "codigoCurso": 611000000133,
                    "glosaGrupoEnsenanza": "Educaci\u00f3n B\u00e1sica",
                    "glosaEnsenanza": "Ense\u00f1anza B\u00e1sica",
                    "glosaNivel": "6\u00b0 b\u00e1sico",
                    "etiquetaNivel": "6BASICO",
                    "sexo": "MIXTO",
                    "glosaJornada": "COMPLETA",
                    "glosaEspecialidad": null,
                    "glosaGrupoPago": "BASICA",
                    "codigoEnsenanza": 110,
                    "codigoNivel": 6,
                    "codigoJornada": 3,
                    "codigoSexo": 3,
                    "codigoEspecialidad": 0,
                    "unicoComuna": false,
                    "proporcionExcelenciaTransicion": null,
                    "proporcionExcelenciaRegimen": null,
                    "proporcionEspecializacionTemprana": null,
                    "copago": {
                        "numeroCuotas": 0,
                        "valorCuota": 0
                    },
                    "cuposTotales": 38,
                    "numeroVacantesRangoInferior": 11,
                    "numeroVacantesRangoSuperior": 14,
                    "porcentajeCambioInferior": 0.0789473684,
                    "procentajeCambioSuperior": 0.1270739064,
                    "cantidadRepitentesAnioActual": 0,
                    "cantidadRepitentesNivelAnterior": 0,
                    "cantidadPreInscritosAnioSiguiente": 30,
                    "cambiosInferior": 2,
                    "cambiosSuperior": 4,
                    "cantidadPreVacantesInferior": 10,
                    "cantidadPreVacantesSuperior": 13,
                    "rango": 2,
                    "numeroPostulantesAnioAnterior": 1,
                    "numeroMovimientoListaEsperaAnoAnterior": 0
                },
                {
                    "codigoCurso": 711000000133,
                    "glosaGrupoEnsenanza": "Educaci\u00f3n B\u00e1sica",
                    "glosaEnsenanza": "Ense\u00f1anza B\u00e1sica",
                    "glosaNivel": "7\u00b0 b\u00e1sico",
                    "etiquetaNivel": "7BASICO",
                    "sexo": "MIXTO",
                    "glosaJornada": "COMPLETA",
                    "glosaEspecialidad": null,
                    "glosaGrupoPago": "BASICA",
                    "codigoEnsenanza": 110,
                    "codigoNivel": 7,
                    "codigoJornada": 3,
                    "codigoSexo": 3,
                    "codigoEspecialidad": 0,
                    "unicoComuna": false,
                    "proporcionExcelenciaTransicion": null,
                    "proporcionExcelenciaRegimen": null,
                    "proporcionEspecializacionTemprana": null,
                    "copago": {
                        "numeroCuotas": 0,
                        "valorCuota": 0
                    },
                    "cuposTotales": 38,
                    "numeroVacantesRangoInferior": 4,
                    "numeroVacantesRangoSuperior": 7,
                    "porcentajeCambioInferior": 0.1050382366,
                    "procentajeCambioSuperior": 0.1434523809,
                    "cantidadRepitentesAnioActual": 0,
                    "cantidadRepitentesNivelAnterior": 0,
                    "cantidadPreInscritosAnioSiguiente": 37,
                    "cambiosInferior": 4,
                    "cambiosSuperior": 5,
                    "cantidadPreVacantesInferior": 4,
                    "cantidadPreVacantesSuperior": 7,
                    "rango": 1,
                    "numeroPostulantesAnioAnterior": 1,
                    "numeroMovimientoListaEsperaAnoAnterior": 0
                },
                {
                    "codigoCurso": 811000000133,
                    "glosaGrupoEnsenanza": "Educaci\u00f3n B\u00e1sica",
                    "glosaEnsenanza": "Ense\u00f1anza B\u00e1sica",
                    "glosaNivel": "8\u00b0 b\u00e1sico",
                    "etiquetaNivel": "8BASICO",
                    "sexo": "MIXTO",
                    "glosaJornada": "COMPLETA",
                    "glosaEspecialidad": null,
                    "glosaGrupoPago": "BASICA",
                    "codigoEnsenanza": 110,
                    "codigoNivel": 8,
                    "codigoJornada": 3,
                    "codigoSexo": 3,
                    "codigoEspecialidad": 0,
                    "unicoComuna": false,
                    "proporcionExcelenciaTransicion": null,
                    "proporcionExcelenciaRegimen": null,
                    "proporcionEspecializacionTemprana": null,
                    "copago": {
                        "numeroCuotas": 0,
                        "valorCuota": 0
                    },
                    "cuposTotales": 38,
                    "numeroVacantesRangoInferior": 6,
                    "numeroVacantesRangoSuperior": 9,
                    "porcentajeCambioInferior": 0.0712398373,
                    "procentajeCambioSuperior": 0.13484167730000002,
                    "cantidadRepitentesAnioActual": 0,
                    "cantidadRepitentesNivelAnterior": 0,
                    "cantidadPreInscritosAnioSiguiente": 34,
                    "cambiosInferior": 2,
                    "cambiosSuperior": 5,
                    "cantidadPreVacantesInferior": 6,
                    "cantidadPreVacantesSuperior": 9,
                    "rango": 3,
                    "numeroPostulantesAnioAnterior": 1,
                    "numeroMovimientoListaEsperaAnoAnterior": 0
                }
            ]
        }
    ],
    "imagenes": [
        {
            "nombre": "FRONTIS+ESCUELA.jpg",
            "principal": true
        },
        {
            "nombre": "ENLACES.jpg",
            "principal": false
        },
        {
            "nombre": "PATIO+TECHADO.jpg",
            "principal": false
        },
        {
            "nombre": "PATIO+KINDER+2_.jpg",
            "principal": false
        },
        {
            "nombre": "CRA..jpg",
            "principal": false
        }
    ],
    "distancia": 0.0,
    "actividades": [
        {
            "tipo": "ACTIVIDADES EXTRAPROGRAM\u00c1TICAS",
            "nombre": "batucada",
            "nivel": "",
            "exigencia": ""
        },
        {
            "tipo": "ACTIVIDADES EXTRAPROGRAM\u00c1TICAS",
            "nombre": "Taller de artes pl\u00e1sticas",
            "nivel": "",
            "exigencia": ""
        },
        {
            "tipo": "ACTIVIDADES EXTRAPROGRAM\u00c1TICAS",
            "nombre": "Taller de m\u00fasica",
            "nivel": "",
            "exigencia": ""
        },
        {
            "tipo": "ACTIVIDADES EXTRAPROGRAM\u00c1TICAS",
            "nombre": "Taller de tecnolog\u00eda de la informaci\u00f3n y\n\t\tcomunicaci\u00f3n",
            "nivel": "",
            "exigencia": ""
        },
        {
            "tipo": "APOYO ACAD\u00c9MICO",
            "nombre": "Asistente Social",
            "nivel": "",
            "exigencia": ""
        },
        {
            "tipo": "APOYO ACAD\u00c9MICO",
            "nombre": "Fonoaudi\u00f3logo",
            "nivel": "",
            "exigencia": ""
        },
        {
            "tipo": "APOYO ACAD\u00c9MICO",
            "nombre": "Kinesi\u00f3logo - Terapeuta Ocupacional",
            "nivel": "",
            "exigencia": ""
        },
        {
            "tipo": "APOYO ACAD\u00c9MICO",
            "nombre": "Profesor de Educaci\u00f3n Especial/Diferencial",
            "nivel": "",
            "exigencia": ""
        },
        {
            "tipo": "APOYO ACAD\u00c9MICO",
            "nombre": "Psic\u00f3logo",
            "nivel": "",
            "exigencia": ""
        },
        {
            "tipo": "APOYO ACAD\u00c9MICO",
            "nombre": "Reforzamiento en materias especificas",
            "nivel": "",
            "exigencia": ""
        },
        {
            "tipo": "DEPORTES",
            "nombre": "B\u00e1squetbol",
            "nivel": "",
            "exigencia": ""
        },
        {
            "tipo": "DEPORTES",
            "nombre": "F\u00fatbol",
            "nivel": "",
            "exigencia": ""
        },
        {
            "tipo": "DEPORTES",
            "nombre": "Nataci\u00f3n",
            "nivel": "",
            "exigencia": ""
        },
        {
            "tipo": "DEPORTES",
            "nombre": "Psicomotricidad",
            "nivel": "",
            "exigencia": ""
        },
        {
            "tipo": "IDIOMA",
            "nombre": "Ingl\u00e9s en educaci\u00f3n b\u00e1sica",
            "nivel": "",
            "exigencia": ""
        },
        {
            "tipo": "INFRAESTRUCTURA",
            "nombre": "Biblioteca",
            "nivel": "",
            "exigencia": ""
        },
        {
            "tipo": "INFRAESTRUCTURA",
            "nombre": "Cancha",
            "nivel": "",
            "exigencia": ""
        },
        {
            "tipo": "INFRAESTRUCTURA",
            "nombre": "Espacios adaptados a necesidades educativas especiales",
            "nivel": "",
            "exigencia": ""
        },
        {
            "tipo": "INFRAESTRUCTURA",
            "nombre": "Laboratorio",
            "nivel": "",
            "exigencia": ""
        },
        {
            "tipo": "INFRAESTRUCTURA",
            "nombre": "Patio techado",
            "nivel": "",
            "exigencia": ""
        },
        {
            "tipo": "INFRAESTRUCTURA",
            "nombre": "Sala de computaci\u00f3n con internet",
            "nivel": "",
            "exigencia": ""
        },
        {
            "tipo": "INFRAESTRUCTURA",
            "nombre": "Sala de uso m\u00faltiple",
            "nivel": "",
            "exigencia": ""
        },
        {
            "tipo": "INFRAESTRUCTURA",
            "nombre": "Tecnolog\u00eda en el aula",
            "nivel": "",
            "exigencia": ""
        },
        {
            "tipo": "PROGRAMAS",
            "nombre": "Actividades de acci\u00f3n social",
            "nivel": "",
            "exigencia": ""
        },
        {
            "tipo": "PROGRAMAS",
            "nombre": "Actividades deportivas",
            "nivel": "",
            "exigencia": ""
        },
        {
            "tipo": "PROGRAMAS",
            "nombre": "Programa de convivencia escolar",
            "nivel": "",
            "exigencia": ""
        },
        {
            "tipo": "PROGRAMAS",
            "nombre": "Programa de cuidado del medio ambiente",
            "nivel": "",
            "exigencia": ""
        },
        {
            "tipo": "PROGRAMAS",
            "nombre": "Programa de educaci\u00f3n sexual",
            "nivel": "",
            "exigencia": ""
        },
        {
            "tipo": "PROGRAMAS",
            "nombre": "Programa de prevenci\u00f3n de drogas y alcohol",
            "nivel": "",
            "exigencia": ""
        },
        {
            "tipo": "PROGRAMAS",
            "nombre": "Programa de promoci\u00f3n de la vida sana",
            "nivel": "",
            "exigencia": ""
        }
    ],
    "procesosEspeciales": [],
    "indicadores": [
        {
            "tipo": "CATEGORIA_DESEMPENIO",
            "titulo": "Insuficiente",
            "nivel": "B\u00e1sica",
            "descripcion": "Muy por debajo de lo esperado",
            "clasificaciones": []
        },
        {
            "tipo": "DESARROLLO_PERSONAL",
            "titulo": "indicadores de desarrollo personal y social",
            "nivel": "B\u00e1sica",
            "descripcion": "",
            "clasificaciones": [
                {
                    "nombreIndicador": "Autoestima acad\u00e9mica y motivaci\u00f3n escolar",
                    "puntaje": 74,
                    "comparacionGseNumero": 1,
                    "comparacionGseGlosa": "Similar"
                },
                {
                    "nombreIndicador": "Clima de convivencia escolar",
                    "puntaje": 75,
                    "comparacionGseNumero": 1,
                    "comparacionGseGlosa": "Similar"
                },
                {
                    "nombreIndicador": "H\u00e1bitos de vida saludable",
                    "puntaje": 67,
                    "comparacionGseNumero": 4,
                    "comparacionGseGlosa": "Similar"
                },
                {
                    "nombreIndicador": "Participaci\u00f3n y formaci\u00f3n ciudadana",
                    "puntaje": 78,
                    "comparacionGseNumero": 0,
                    "comparacionGseGlosa": "Similar"
                }
            ]
        },
        {
            "tipo": "SIMCE",
            "titulo": "Resultados SIMCE 2018",
            "nivel": "B\u00e1sica",
            "descripcion": "",
            "clasificaciones": [
                {
                    "nombreIndicador": "Lenguaje",
                    "puntaje": 237,
                    "comparacionGseNumero": 9,
                    "comparacionGseGlosa": "M\u00e1s alto"
                },
                {
                    "nombreIndicador": "Matem\u00e1tica",
                    "puntaje": 254,
                    "comparacionGseNumero": 1,
                    "comparacionGseGlosa": "Similar"
                }
            ]
        }
    ],
    "especialidades": []
}