{"id": "5ced4dfdef59fa0001b1fcc8", "rbd": 3801, "nombre": "ESCUELA NIQUEN", "dependencia": "PUBLICO", "telefono": "2341147", "mail": "PROFEKARENBASCU@GMAIL.COM", "url": "", "habilitadoPostular": true, "habilitadoVitrina": true, "nivelMinimo": "Pre-Kinder", "nivelMaximo": "8\u00ba B\u00e1sico", "director": {"nombre": "KAREN LORETO BASCU\u00d1\u00c1N BURGOS"}, "etiquetas": ["PIE", "SEP", "GRATUITO"], "informacionInstitucional": {"resumenProyecto": "El Proyecto Educativo de la Escuela \u00d1iqu\u00e9n se encuentra sustentado dentro del Marco Legal que rige a los Establecimientos Educacionales de todo el pa\u00eds.\r\nSe centra en la concepci\u00f3n humanista del hombre y en la l\u00ednea constructivista del aprendizaje que se\u00f1ala que los estudiantes aprenden haciendo y son los constructores de su propio aprendizaje.\r\n\r\nEn \u00e9l se encuentran insertos la Visi\u00f3n y Misi\u00f3n as\u00ed como sus sellos identitarios que rigen todo el quehacer de la Unidad Educativa.\r\n\r\nEn su Visi\u00f3n y Misi\u00f3n se se\u00f1ala que el objetivo de la Escuela es entregar las herramientas necesarias al estudiantes para que desarrolle todas sus habilidades y potenciarlas para la prosecuci\u00f3n de estudios en Ense\u00f1anza Media y logre tener \u00e9xito en su futuro.\r\n\r\nAdem\u00e1s, de adquirir destrezas en el \u00e1rea acad\u00e9mica,social, afectiva y de convivencia, la educaci\u00f3n de los estudiantes propende hacia la formaci\u00f3n de un ser humano tolerante, respetuoso, medio ambientalista e inclusivo.\r\n\r\nEl PEI de la Escuela \u00d1iqu\u00e9n, traza el rumbo de su quehacer institucional en la entrega de aprendizajes de calidad, en la valoraci\u00f3n de la instituci\u00f3n formadora y en la inclusividad como un medio para alcanzar el \u00e9xito.\r\n", "documentoProyecto": "ProyectoEducativo3801.pdf", "documentoReglamento": "ReglamentodeConvivencia3801.pdf", "internado": false, "integracion": true, "subvencionPreferencial": true, "peib": false, "politicaUniforme": "Uniforme propio", "orientacionReligiosa": "Laica", "alumnosMatriculados": 132, "promedioAlumnosPorCurso": 13, "cantidadDocentes": 20, "regimen": "Mixto"}, "sedes": [{"codigoSede": 1, "direccion": {"codigoRegion": 16, "codigoComuna": 16303, "region": "De \u00d1uble", "comuna": "\u00d1iqu\u00e9n", "calle": "PABLO SUBERCASEAUX S/N \u00d1IQUEN ESTACI\u00d3N S/N", "coordenadas": {"type": "Point", "coordinates": [-71.90082, -36.29446]}}, "niveles": [{"codigoCurso": 401000000133, "glosaGrupoEnsenanza": "Educaci\u00f3n Parvularia", "glosaEnsenanza": "Educaci\u00f3n Parvularia", "glosaNivel": "1er nivel de Transici\u00f3n (Pre-kinder)", "etiquetaNivel": "PREKINDER", "sexo": "MIXTO", "glosaJornada": "COMPLETA", "glosaEspecialidad": null, "glosaGrupoPago": "PARVULARIA", "codigoEnsenanza": 10, "codigoNivel": 4, "codigoJornada": 3, "codigoSexo": 3, "codigoEspecialidad": 0, "unicoComuna": true, "proporcionExcelenciaTransicion": null, "proporcionExcelenciaRegimen": null, "proporcionEspecializacionTemprana": null, "copago": {"numeroCuotas": 0, "valorCuota": 0}, "cuposTotales": 40, "numeroVacantesRangoInferior": 36, "numeroVacantesRangoSuperior": 36, "porcentajeCambioInferior": 0.0, "procentajeCambioSuperior": 0.0, "cantidadRepitentesAnioActual": 0, "cantidadRepitentesNivelAnterior": 0, "cantidadPreInscritosAnioSiguiente": 0, "cambiosInferior": 0, "cambiosSuperior": 0, "cantidadPreVacantesInferior": 40, "cantidadPreVacantesSuperior": 40, "rango": 0, "numeroPostulantesAnioAnterior": 1, "numeroMovimientoListaEsperaAnoAnterior": 0}, {"codigoCurso": 501000000133, "glosaGrupoEnsenanza": "Educaci\u00f3n Parvularia", "glosaEnsenanza": "Educaci\u00f3n Parvularia", "glosaNivel": "2\u00b0 nivel de Transici\u00f3n (Kinder)", "etiquetaNivel": "KINDER", "sexo": "MIXTO", "glosaJornada": "COMPLETA", "glosaEspecialidad": null, "glosaGrupoPago": "PARVULARIA", "codigoEnsenanza": 10, "codigoNivel": 5, "codigoJornada": 3, "codigoSexo": 3, "codigoEspecialidad": 0, "unicoComuna": true, "proporcionExcelenciaTransicion": null, "proporcionExcelenciaRegimen": null, "proporcionEspecializacionTemprana": null, "copago": {"numeroCuotas": 0, "valorCuota": 0}, "cuposTotales": 40, "numeroVacantesRangoInferior": 30, "numeroVacantesRangoSuperior": 30, "porcentajeCambioInferior": 0.0, "procentajeCambioSuperior": 0.14377289370000002, "cantidadRepitentesAnioActual": 0, "cantidadRepitentesNivelAnterior": 0, "cantidadPreInscritosAnioSiguiente": 12, "cambiosInferior": 0, "cambiosSuperior": 2, "cantidadPreVacantesInferior": 28, "cantidadPreVacantesSuperior": 31, "rango": 2, "numeroPostulantesAnioAnterior": 1, "numeroMovimientoListaEsperaAnoAnterior": 0}, {"codigoCurso": 111000000133, "glosaGrupoEnsenanza": "Educaci\u00f3n B\u00e1sica", "glosaEnsenanza": "Ense\u00f1anza B\u00e1sica", "glosaNivel": "1\u00b0 b\u00e1sico", "etiquetaNivel": "1BASICO", "sexo": "MIXTO", "glosaJornada": "COMPLETA", "glosaEspecialidad": null, "glosaGrupoPago": "BASICA", "codigoEnsenanza": 110, "codigoNivel": 1, "codigoJornada": 3, "codigoSexo": 3, "codigoEspecialidad": 0, "unicoComuna": true, "proporcionExcelenciaTransicion": null, "proporcionExcelenciaRegimen": null, "proporcionEspecializacionTemprana": null, "copago": {"numeroCuotas": 0, "valorCuota": 0}, "cuposTotales": 40, "numeroVacantesRangoInferior": 34, "numeroVacantesRangoSuperior": 34, "porcentajeCambioInferior": 0.0, "procentajeCambioSuperior": 0.11226851850000001, "cantidadRepitentesAnioActual": 2, "cantidadRepitentesNivelAnterior": 0, "cantidadPreInscritosAnioSiguiente": 5, "cambiosInferior": 0, "cambiosSuperior": 1, "cantidadPreVacantesInferior": 32, "cantidadPreVacantesSuperior": 35, "rango": 1, "numeroPostulantesAnioAnterior": 0, "numeroMovimientoListaEsperaAnoAnterior": 0}, {"codigoCurso": 211000000133, "glosaGrupoEnsenanza": "Educaci\u00f3n B\u00e1sica", "glosaEnsenanza": "Ense\u00f1anza B\u00e1sica", "glosaNivel": "2\u00b0 b\u00e1sico", "etiquetaNivel": "2BASICO", "sexo": "MIXTO", "glosaJornada": "COMPLETA", "glosaEspecialidad": null, "glosaGrupoPago": "BASICA", "codigoEnsenanza": 110, "codigoNivel": 2, "codigoJornada": 3, "codigoSexo": 3, "codigoEspecialidad": 0, "unicoComuna": true, "proporcionExcelenciaTransicion": null, "proporcionExcelenciaRegimen": null, "proporcionEspecializacionTemprana": null, "copago": {"numeroCuotas": 0, "valorCuota": 0}, "cuposTotales": 40, "numeroVacantesRangoInferior": 27, "numeroVacantesRangoSuperior": 27, "porcentajeCambioInferior": 0.0, "procentajeCambioSuperior": 0.10637254900000001, "cantidadRepitentesAnioActual": 2, "cantidadRepitentesNivelAnterior": 2, "cantidadPreInscritosAnioSiguiente": 15, "cambiosInferior": 0, "cambiosSuperior": 2, "cantidadPreVacantesInferior": 25, "cantidadPreVacantesSuperior": 28, "rango": 2, "numeroPostulantesAnioAnterior": 1, "numeroMovimientoListaEsperaAnoAnterior": 0}, {"codigoCurso": 311000000133, "glosaGrupoEnsenanza": "Educaci\u00f3n B\u00e1sica", "glosaEnsenanza": "Ense\u00f1anza B\u00e1sica", "glosaNivel": "3\u00b0 b\u00e1sico", "etiquetaNivel": "3BASICO", "sexo": "MIXTO", "glosaJornada": "COMPLETA", "glosaEspecialidad": null, "glosaGrupoPago": "BASICA", "codigoEnsenanza": 110, "codigoNivel": 3, "codigoJornada": 3, "codigoSexo": 3, "codigoEspecialidad": 0, "unicoComuna": true, "proporcionExcelenciaTransicion": null, "proporcionExcelenciaRegimen": null, "proporcionEspecializacionTemprana": null, "copago": {"numeroCuotas": 0, "valorCuota": 0}, "cuposTotales": 40, "numeroVacantesRangoInferior": 28, "numeroVacantesRangoSuperior": 28, "porcentajeCambioInferior": 0.0, "procentajeCambioSuperior": 0.1557315233, "cantidadRepitentesAnioActual": 0, "cantidadRepitentesNivelAnterior": 2, "cantidadPreInscritosAnioSiguiente": 15, "cambiosInferior": 0, "cambiosSuperior": 2, "cantidadPreVacantesInferior": 27, "cantidadPreVacantesSuperior": 30, "rango": 2, "numeroPostulantesAnioAnterior": 0, "numeroMovimientoListaEsperaAnoAnterior": 0}, {"codigoCurso": 411000000133, "glosaGrupoEnsenanza": "Educaci\u00f3n B\u00e1sica", "glosaEnsenanza": "Ense\u00f1anza B\u00e1sica", "glosaNivel": "4\u00b0 b\u00e1sico", "etiquetaNivel": "4BASICO", "sexo": "MIXTO", "glosaJornada": "COMPLETA", "glosaEspecialidad": null, "glosaGrupoPago": "BASICA", "codigoEnsenanza": 110, "codigoNivel": 4, "codigoJornada": 3, "codigoSexo": 3, "codigoEspecialidad": 0, "unicoComuna": true, "proporcionExcelenciaTransicion": null, "proporcionExcelenciaRegimen": null, "proporcionEspecializacionTemprana": null, "copago": {"numeroCuotas": 0, "valorCuota": 0}, "cuposTotales": 40, "numeroVacantesRangoInferior": 24, "numeroVacantesRangoSuperior": 24, "porcentajeCambioInferior": 0.0, "procentajeCambioSuperior": 0.0059523809, "cantidadRepitentesAnioActual": 0, "cantidadRepitentesNivelAnterior": 0, "cantidadPreInscritosAnioSiguiente": 15, "cambiosInferior": 0, "cambiosSuperior": 0, "cantidadPreVacantesInferior": 24, "cantidadPreVacantesSuperior": 27, "rango": 0, "numeroPostulantesAnioAnterior": 0, "numeroMovimientoListaEsperaAnoAnterior": 0}, {"codigoCurso": 511000000133, "glosaGrupoEnsenanza": "Educaci\u00f3n B\u00e1sica", "glosaEnsenanza": "Ense\u00f1anza B\u00e1sica", "glosaNivel": "5\u00b0 b\u00e1sico", "etiquetaNivel": "5BASICO", "sexo": "MIXTO", "glosaJornada": "COMPLETA", "glosaEspecialidad": null, "glosaGrupoPago": "BASICA", "codigoEnsenanza": 110, "codigoNivel": 5, "codigoJornada": 3, "codigoSexo": 3, "codigoEspecialidad": 0, "unicoComuna": true, "proporcionExcelenciaTransicion": null, "proporcionExcelenciaRegimen": null, "proporcionEspecializacionTemprana": null, "copago": {"numeroCuotas": 0, "valorCuota": 0}, "cuposTotales": 40, "numeroVacantesRangoInferior": 26, "numeroVacantesRangoSuperior": 26, "porcentajeCambioInferior": 0.0, "procentajeCambioSuperior": 0.0875, "cantidadRepitentesAnioActual": 0, "cantidadRepitentesNivelAnterior": 0, "cantidadPreInscritosAnioSiguiente": 15, "cambiosInferior": 0, "cambiosSuperior": 1, "cantidadPreVacantesInferior": 24, "cantidadPreVacantesSuperior": 27, "rango": 1, "numeroPostulantesAnioAnterior": 0, "numeroMovimientoListaEsperaAnoAnterior": 0}, {"codigoCurso": 611000000133, "glosaGrupoEnsenanza": "Educaci\u00f3n B\u00e1sica", "glosaEnsenanza": "Ense\u00f1anza B\u00e1sica", "glosaNivel": "6\u00b0 b\u00e1sico", "etiquetaNivel": "6BASICO", "sexo": "MIXTO", "glosaJornada": "COMPLETA", "glosaEspecialidad": null, "glosaGrupoPago": "BASICA", "codigoEnsenanza": 110, "codigoNivel": 6, "codigoJornada": 3, "codigoSexo": 3, "codigoEspecialidad": 0, "unicoComuna": true, "proporcionExcelenciaTransicion": null, "proporcionExcelenciaRegimen": null, "proporcionEspecializacionTemprana": null, "copago": {"numeroCuotas": 0, "valorCuota": 0}, "cuposTotales": 40, "numeroVacantesRangoInferior": 28, "numeroVacantesRangoSuperior": 28, "porcentajeCambioInferior": 0.0, "procentajeCambioSuperior": 0.10681818180000001, "cantidadRepitentesAnioActual": 0, "cantidadRepitentesNivelAnterior": 0, "cantidadPreInscritosAnioSiguiente": 13, "cambiosInferior": 0, "cambiosSuperior": 1, "cantidadPreVacantesInferior": 26, "cantidadPreVacantesSuperior": 29, "rango": 1, "numeroPostulantesAnioAnterior": 0, "numeroMovimientoListaEsperaAnoAnterior": 0}, {"codigoCurso": 711000000133, "glosaGrupoEnsenanza": "Educaci\u00f3n B\u00e1sica", "glosaEnsenanza": "Ense\u00f1anza B\u00e1sica", "glosaNivel": "7\u00b0 b\u00e1sico", "etiquetaNivel": "7BASICO", "sexo": "MIXTO", "glosaJornada": "COMPLETA", "glosaEspecialidad": null, "glosaGrupoPago": "BASICA", "codigoEnsenanza": 110, "codigoNivel": 7, "codigoJornada": 3, "codigoSexo": 3, "codigoEspecialidad": 0, "unicoComuna": true, "proporcionExcelenciaTransicion": null, "proporcionExcelenciaRegimen": null, "proporcionEspecializacionTemprana": null, "copago": {"numeroCuotas": 0, "valorCuota": 0}, "cuposTotales": 40, "numeroVacantesRangoInferior": 23, "numeroVacantesRangoSuperior": 23, "porcentajeCambioInferior": 0.0, "procentajeCambioSuperior": 0.1014705882, "cantidadRepitentesAnioActual": 2, "cantidadRepitentesNivelAnterior": 0, "cantidadPreInscritosAnioSiguiente": 15, "cambiosInferior": 0, "cambiosSuperior": 2, "cantidadPreVacantesInferior": 23, "cantidadPreVacantesSuperior": 26, "rango": 2, "numeroPostulantesAnioAnterior": 0, "numeroMovimientoListaEsperaAnoAnterior": 0}, {"codigoCurso": 811000000133, "glosaGrupoEnsenanza": "Educaci\u00f3n B\u00e1sica", "glosaEnsenanza": "Ense\u00f1anza B\u00e1sica", "glosaNivel": "8\u00b0 b\u00e1sico", "etiquetaNivel": "8BASICO", "sexo": "MIXTO", "glosaJornada": "COMPLETA", "glosaEspecialidad": null, "glosaGrupoPago": "BASICA", "codigoEnsenanza": 110, "codigoNivel": 8, "codigoJornada": 3, "codigoSexo": 3, "codigoEspecialidad": 0, "unicoComuna": true, "proporcionExcelenciaTransicion": null, "proporcionExcelenciaRegimen": null, "proporcionEspecializacionTemprana": null, "copago": {"numeroCuotas": 0, "valorCuota": 0}, "cuposTotales": 40, "numeroVacantesRangoInferior": 33, "numeroVacantesRangoSuperior": 33, "porcentajeCambioInferior": 0.0, "procentajeCambioSuperior": 0.1407407407, "cantidadRepitentesAnioActual": 0, "cantidadRepitentesNivelAnterior": 2, "cantidadPreInscritosAnioSiguiente": 9, "cambiosInferior": 0, "cambiosSuperior": 1, "cantidadPreVacantesInferior": 32, "cantidadPreVacantesSuperior": 35, "rango": 1, "numeroPostulantesAnioAnterior": 0, "numeroMovimientoListaEsperaAnoAnterior": 0}]}], "imagenes": [{"nombre": "Portada.jpg", "principal": true}, {"nombre": "20170511_123808.jpg", "principal": false}, {"nombre": "Comedor.jpg", "principal": false}], "distancia": 0.0, "actividades": [{"tipo": "ACTIVIDADES EXTRAPROGRAM\u00c1TICAS", "nombre": "Patinaje", "nivel": "", "exigencia": ""}, {"tipo": "ACTIVIDADES EXTRAPROGRAM\u00c1TICAS", "nombre": "Taller de m\u00fasica", "nivel": "", "exigencia": ""}, {"tipo": "ACTIVIDADES EXTRAPROGRAM\u00c1TICAS", "nombre": "Taller de teatro", "nivel": "", "exigencia": ""}, {"tipo": "APOYO ACAD\u00c9MICO", "nombre": "Asistente Social", "nivel": "", "exigencia": ""}, {"tipo": "APOYO ACAD\u00c9MICO", "nombre": "Fonoaudi\u00f3logo", "nivel": "", "exigencia": ""}, {"tipo": "APOYO ACAD\u00c9MICO", "nombre": "Orientador", "nivel": "", "exigencia": ""}, {"tipo": "APOYO ACAD\u00c9MICO", "nombre": "Profesor de Educaci\u00f3n Especial/Diferencial", "nivel": "", "exigencia": ""}, {"tipo": "APOYO ACAD\u00c9MICO", "nombre": "Psic\u00f3logo", "nivel": "", "exigencia": ""}, {"tipo": "APOYO ACAD\u00c9MICO", "nombre": "Reforzamiento en materias especificas", "nivel": "", "exigencia": ""}, {"tipo": "DEPORTES", "nombre": "Baby F\u00fatbol", "nivel": "", "exigencia": ""}, {"tipo": "DEPORTES", "nombre": "Tenis de mesa", "nivel": "", "exigencia": ""}, {"tipo": "IDIOMA", "nombre": "Ingl\u00e9s en educaci\u00f3n b\u00e1sica", "nivel": "", "exigencia": ""}, {"tipo": "INFRAESTRUCTURA", "nombre": "Biblioteca", "nivel": "", "exigencia": ""}, {"tipo": "INFRAESTRUCTURA", "nombre": "Cancha", "nivel": "", "exigencia": ""}, {"tipo": "INFRAESTRUCTURA", "nombre": "Espacios adaptados a necesidades educativas especiales", "nivel": "", "exigencia": ""}, {"tipo": "INFRAESTRUCTURA", "nombre": "Sala de computaci\u00f3n con internet", "nivel": "", "exigencia": ""}, {"tipo": "INFRAESTRUCTURA", "nombre": "Sala de uso m\u00faltiple", "nivel": "", "exigencia": ""}, {"tipo": "INFRAESTRUCTURA", "nombre": "Tecnolog\u00eda en el aula", "nivel": "", "exigencia": ""}, {"tipo": "PROGRAMAS", "nombre": "Orientaci\u00f3n", "nivel": "", "exigencia": ""}, {"tipo": "PROGRAMAS", "nombre": "Programa de convivencia escolar", "nivel": "", "exigencia": ""}, {"tipo": "PROGRAMAS", "nombre": "Programa de educaci\u00f3n sexual", "nivel": "", "exigencia": ""}, {"tipo": "PROGRAMAS", "nombre": "Programa de promoci\u00f3n de la vida sana", "nivel": "", "exigencia": ""}], "procesosEspeciales": [], "indicadores": [{"tipo": "CATEGORIA_DESEMPENIO", "titulo": "Medio", "nivel": "B\u00e1sica", "descripcion": "Similares a lo esperado", "clasificaciones": []}, {"tipo": "DESARROLLO_PERSONAL", "titulo": "indicadores de desarrollo personal y social", "nivel": "B\u00e1sica", "descripcion": "", "clasificaciones": [{"nombreIndicador": "Autoestima acad\u00e9mica y motivaci\u00f3n escolar", "puntaje": 78, "comparacionGseNumero": 3, "comparacionGseGlosa": "Similar"}, {"nombreIndicador": "Clima de convivencia escolar", "puntaje": 82, "comparacionGseNumero": 6, "comparacionGseGlosa": "M\u00e1s alto"}, {"nombreIndicador": "H\u00e1bitos de vida saludable", "puntaje": 84, "comparacionGseNumero": 13, "comparacionGseGlosa": "M\u00e1s alto"}, {"nombreIndicador": "Participaci\u00f3n y formaci\u00f3n ciudadana", "puntaje": 90, "comparacionGseNumero": 12, "comparacionGseGlosa": "M\u00e1s alto"}]}, {"tipo": "SIMCE", "titulo": "Resultados SIMCE 2018", "nivel": "B\u00e1sica", "descripcion": "", "clasificaciones": [{"nombreIndicador": "Lenguaje", "puntaje": 266, "comparacionGseNumero": 38, "comparacionGseGlosa": "M\u00e1s alto"}, {"nombreIndicador": "Matem\u00e1tica", "puntaje": 271, "comparacionGseNumero": 1, "comparacionGseGlosa": "M\u00e1s alto"}]}], "especialidades": []}